semantic_search_nollms/__init__.py
semantic_search_nollms/data_loader.py
semantic_search_nollms/document_processor.py
semantic_search_nollms/main.py
semantic_search_nollms/utils.py
semantic_search_nollms/web_crawler.py
semantic_search_nollms-0.3.dist-info/METADATA
semantic_search_nollms-0.3.dist-info/WHEEL
semantic_search_nollms-0.3.dist-info/entry_points.txt
semantic_search_nollms-0.3.dist-info/top_level.txt
semantic_search_nollms-0.3.dist-info/RECORD
