Metadata-Version: 2.1
Name: semantic_search_nollms
Version: 0.3
Requires-Dist: streamlit
Requires-Dist: requests
Requires-Dist: beautifulsoup4
Requires-Dist: pandas
Requires-Dist: docx2txt
Requires-Dist: langchain
Requires-Dist: langchain-community
Requires-Dist: langchain-text-splitters
Requires-Dist: faiss-cpu
Requires-Dist: numpy
Requires-Dist: Pillow
Requires-Dist: pytesseract
Requires-Dist: PyPDF2
